pyglaze/__init__.py
pyglaze/py.typed
pyglaze/datamodels/__init__.py
pyglaze/datamodels/pulse.py
pyglaze/datamodels/waveform.py
pyglaze/device/__init__.py
pyglaze/device/ampcom.py
pyglaze/device/configuration.py
pyglaze/devtools/__init__.py
pyglaze/devtools/mock_device.py
pyglaze/devtools/thz_pulse.py
pyglaze/helpers/__init__.py
pyglaze/helpers/_lockin.py
pyglaze/helpers/_types.py
pyglaze/helpers/utilities.py
pyglaze/interpolation/__init__.py
pyglaze/interpolation/interpolation.py
pyglaze/scanning/__init__.py
pyglaze/scanning/_asyncscanner.py
pyglaze/scanning/_exceptions.py
pyglaze/scanning/client.py
pyglaze/scanning/scanner.py
pyglaze-0.4.7.dist-info/licenses/LICENSE
pyglaze-0.4.7.dist-info/METADATA
pyglaze-0.4.7.dist-info/WHEEL
pyglaze-0.4.7.dist-info/top_level.txt
pyglaze-0.4.7.dist-info/RECORD
