Metadata-Version: 2.4
Name: pyglaze
Version: 0.4.7
Summary: Pyglaze is a library used to operate the devices of Glaze Technologies
Author: GLAZE Technologies ApS
License: BSD 3-Clause License
Project-URL: Homepage, https://www.glazetech.dk/
Project-URL: Documentation, https://glazetech.github.io/pyglaze/latest
Project-URL: Repository, https://github.com/GlazeTech/pyglaze
Project-URL: Issues, https://github.com/GlazeTech/pyglaze/issues
Requires-Python: <3.14,>=3.9
License-File: LICENSE
Requires-Dist: numpy<2.0.0,>=1.26.4
Requires-Dist: pyserial>=3.5
Requires-Dist: scipy>=1.7.3
Requires-Dist: bitstring>=4.1.2
Requires-Dist: typing_extensions>=4.12.2
Provides-Extra: build
Requires-Dist: build>=1.2.1; extra == "build"
Requires-Dist: twine>=5.1.1; extra == "build"
Requires-Dist: bumpver>=2023.1129; extra == "build"
Provides-Extra: test
Requires-Dist: pytest>=7.0.1; extra == "test"
Requires-Dist: pytest-cov>=4.0.0; extra == "test"
Provides-Extra: docs
Requires-Dist: mkdocs>=1.2.3; extra == "docs"
Requires-Dist: mkdocs-material>=8.2.5; extra == "docs"
Requires-Dist: mkdocstrings[python]>=0.18.1; extra == "docs"
Requires-Dist: mike>=1.1.2; extra == "docs"
Requires-Dist: Pygments>=2.12.0; extra == "docs"
Requires-Dist: matplotlib>=3.7.0; extra == "docs"
Requires-Dist: bumpver>=2023.1129; extra == "docs"
Provides-Extra: dev
Requires-Dist: ruff>=0.14.10; extra == "dev"
Requires-Dist: ty>=0.0.13; extra == "dev"
Requires-Dist: pytest>=7.0.1; extra == "dev"
Requires-Dist: pytest-cov>=4.0.0; extra == "dev"
Requires-Dist: semver>=2.13.0; extra == "dev"
Requires-Dist: types-pyserial>=3.5.0.8; extra == "dev"
Requires-Dist: bumpver>=2023.1129; extra == "dev"
Dynamic: license-file
